cloudtoken/core/__init__.py
cloudtoken/core/__main__.py
cloudtoken/core/abstract_classes.py
cloudtoken/core/cli.py
cloudtoken/core/core.py
cloudtoken/core/daemon.py
cloudtoken/core/exceptions.py
cloudtoken/core/helper_classes.py
cloudtoken/core/networking.py
cloudtoken/core/utils.py
cloudtoken/plugins/assume_role/__init__.py
cloudtoken/plugins/assume_role/plugin.py
cloudtoken/plugins/export_credentials_awscli/__init__.py
cloudtoken/plugins/export_credentials_awscli/plugin.py
cloudtoken/plugins/export_credentials_json/__init__.py
cloudtoken/plugins/export_credentials_json/plugin.py
cloudtoken/plugins/export_credentials_shell/__init__.py
cloudtoken/plugins/export_credentials_shell/plugin.py
cloudtoken/plugins/google_aws/__init__.py
cloudtoken/plugins/google_aws/google_auth.py
cloudtoken/plugins/google_aws/plugin.py
cloudtoken/plugins/idaptive/__init__.py
cloudtoken/plugins/idaptive/mechanisms/__init__.py
cloudtoken/plugins/idaptive/mechanisms/duo.py
cloudtoken/plugins/idaptive/mechanisms/radius.py
cloudtoken/plugins/idaptive/mechanisms/u2f.py
cloudtoken/plugins/idaptive/mechanisms/up.py
cloudtoken/plugins/idaptive/plugin.py
cloudtoken/plugins/okta/__init__.py
cloudtoken/plugins/okta/enums.py
cloudtoken/plugins/okta/exceptions.py
cloudtoken/plugins/okta/factors/__init__.py
cloudtoken/plugins/okta/factors/push.py
cloudtoken/plugins/okta/factors/totp.py
cloudtoken/plugins/okta/plugin.py
cloudtoken/plugins/saml/__init__.py
cloudtoken/plugins/saml/plugin.py
cloudtoken/plugins/url_generator/__init__.py
cloudtoken/plugins/url_generator/plugin.py
cloudtoken-2.1.18.dist-info/LICENSE
cloudtoken-2.1.18.dist-info/METADATA
cloudtoken-2.1.18.dist-info/WHEEL
cloudtoken-2.1.18.dist-info/entry_points.txt
cloudtoken-2.1.18.dist-info/RECORD
