Metadata-Version: 2.1
Name: cloudtoken
Version: 2.1.18
Summary: AWS Token Vending assuming roles
Author: Cloud Engineering
Author-email: cloud-team@atlassian.com
Requires-Python: >=3.8,<4.0
Classifier: Programming Language :: Python :: 3
Classifier: Programming Language :: Python :: 3.8
Classifier: Programming Language :: Python :: 3.9
Classifier: Programming Language :: Python :: 3.10
Classifier: Programming Language :: Python :: 3.11
Classifier: Programming Language :: Python :: 3.12
Requires-Dist: Flask (==2.3.3)
Requires-Dist: appdirs (>=1.4.4,<2.0.0)
Requires-Dist: boto3 (>=1.16.25,<2.0.0)
Requires-Dist: cryptography (>=42.0.5,<43.0.0)
Requires-Dist: deepdiff (>=5.0.2,<6.0.0)
Requires-Dist: delegator.py (>=0.1.1,<0.2.0)
Requires-Dist: halo (>=0.0.31,<0.0.32)
Requires-Dist: ifaddr (>=0.1.7,<0.2.0)
Requires-Dist: keyring (>=25.0.0,<26.0.0)
Requires-Dist: lxml (==4.9.2)
Requires-Dist: packaging (>=20.7,<21.0)
Requires-Dist: requests (>=2.25.0,<3.0.0)
Requires-Dist: ruamel.yaml (>=0.17.4,<0.18.0)
Requires-Dist: urllib3 (>=1.25.4,<1.27)
Requires-Dist: werkzeug (==3.0.3)
Requires-Dist: xdg (>=5.0.1,<6.0.0)
